LICENSE
MANIFEST.in
README.rst
setup.py
python_veralite.egg-info/PKG-INFO
python_veralite.egg-info/SOURCES.txt
python_veralite.egg-info/dependency_links.txt
python_veralite.egg-info/entry_points.txt
python_veralite.egg-info/requires.txt
python_veralite.egg-info/top_level.txt
test/test_veralite.py
veralite/__init__.py
veralite/command_line.py
veralite/device.py
veralite/exceptions.py
veralite/scene.py
veralite/utils.py
veralite/veralite.py