Metadata-Version: 1.1
Name: python-veralite
Version: 0.0.2
Summary: Python API and command line tool for talking to the Veralite™ Smart Home Controller
Home-page: https://github.com/zgreatone/python-veralite/
Author: Okpe Pessu
Author-email: opessu@zgreatone.net
License: UNKNOWN
Keywords: veralite
Platform: UNKNOWN
Classifier: Development Status :: 3 - Alpha
Classifier: Intended Audience :: Developers
Classifier: Topic :: Utilities
